sabnzbd_api/__init__.py
sabnzbd_api/bound_methods.py
sabnzbd_api/exception.py
sabnzbd_api/job_functions.py
sabnzbd_api/requests.py
sabnzbd_api-0.1.2.dist-info/LICENSE
sabnzbd_api-0.1.2.dist-info/METADATA
sabnzbd_api-0.1.2.dist-info/WHEEL
sabnzbd_api-0.1.2.dist-info/top_level.txt
sabnzbd_api-0.1.2.dist-info/RECORD
