Metadata-Version: 2.1
Name: sabnzbd-api
Version: 0.1.2
Summary: Complete API wrapper for the usenet downloading tool SABnzbd
Home-page: UNKNOWN
Author: Andrews Jack
Author-email: 
License: MIT
Keywords: sabnzbd client api wrapper
Platform: UNKNOWN
Classifier: Programming Language :: Python :: 3
Classifier: License :: OSI Approved :: MIT License
Classifier: Operating System :: OS Independent
Requires-Python: >=3.6
Requires-Dist: httpx
Requires-Dist: urllib3
